{
  "dewpt": "Тачка росе",
  "elev": "Надморска висина",
  "heatIndex": "Топлотни индекс",
  "humidity": "Релативна влажност",
  "neighborhood": "Комшилук",
  "obsTimeLocal": "Локално време посматрања",
  "precipRate": "Стопа падавина",
  "precipTotal": "Падавине данас",
  "pressure": "Притисак",
  "solarRadiation": "Сунчево зрачење",
  "stationID": "ИД станице",
  "temp": "Температура",
  "uv": "УВ индек",
  "windChill": "Винд Цхилл",
  "windDirectionCardinal": "Смер ветра - кардинални",
  "windGust": "Удари ветра",
  "windSpeed": "Брзина ветра",
  "winddir": "Смер ветра - степени",
  "narrative": "Веатхер Суммари",
  "qpfSnow": "Количина снега",
  "daypart": {
    "expired": "Тодаи Екпиред",
    "narrative": "Сажетак прогнозе",
    "precipChance": "Вероватноћа падавина",
    "qpf": "Количина падавина",
    "temperature": "Прогноза температуре",
    "windSpeed": "Авераге Винд"
  }
}